gscdk
