Metadata-Version: 2.1
Name: gscdk
Version: 0.6.3
Summary: Go Smart Contract Development Kit
Home-page: https://github.com/uuosio/uuosio.gscdk
Author: The UUOSIO Team
License: BSD-3-Clause
Platform: UNKNOWN
License-File: LICENSE
